chmpy/__init__.py
chmpy/main.py
chmpy/main.tcss
chmpy_sp-0.3.4.dist-info/licenses/LICENSE
chmpy_sp-0.3.4.dist-info/METADATA
chmpy_sp-0.3.4.dist-info/WHEEL
chmpy_sp-0.3.4.dist-info/entry_points.txt
chmpy_sp-0.3.4.dist-info/top_level.txt
chmpy_sp-0.3.4.dist-info/RECORD
