Metadata-Version: 2.4
Name: chmpy-sp
Version: 0.3.4
Summary: python TUI for chaning file/folder permission
Author: Ammar Syamil
Author-email: ammarsyamil057@gmail.com
License: MIT
License-File: LICENSE
Requires-Dist: textual>=0.74.0
Requires-Dist: art
Dynamic: author
Dynamic: author-email
Dynamic: description
Dynamic: description-content-type
Dynamic: license
Dynamic: license-file
Dynamic: requires-dist
Dynamic: summary
